metaxuda/__init__.py
metaxuda/buffer.py
metaxuda/env.py
metaxuda/patch.py
metaxuda/pipeline.py
metaxuda/pool.py
metaxuda/stream.py
metaxuda/demos/add.py
metaxuda/demos/buffers.py
metaxuda/demos/demo.py
metaxuda/demos/fusion.py
metaxuda/demos/large_buffer.py
metaxuda/demos/matrix_mul.py
metaxuda/demos/non_tiered_buffer_test.py
metaxuda/demos/streams.py
metaxuda/demos/tiered_buffer_test.py
metaxuda/native/libcuda.dylib
metaxuda/native/libcudart.dylib
metaxuda/native/libdevice.bc
metaxuda/native/libnvvm.dylib
metaxuda-0.1.8.dist-info/METADATA
metaxuda-0.1.8.dist-info/WHEEL
metaxuda-0.1.8.dist-info/top_level.txt
metaxuda-0.1.8.dist-info/RECORD
