Metadata-Version: 2.4
Name: metaxuda
Version: 0.1.8
Summary: CUDA→Metal universal backend shim (MetaXuda)
Author-email: Perinban Parameshwaran <p.perinban@gmail.com>
License: MIT
Classifier: Development Status :: 3 - Alpha
Classifier: Intended Audience :: Developers
Classifier: Programming Language :: Python :: 3
Classifier: Operating System :: MacOS
Classifier: License :: OSI Approved :: MIT License
Requires-Python: >=3.8
Requires-Dist: numpy>=1.21
Requires-Dist: numba>=0.57
